consentdb/__init__.py
consentdb/admin.py
consentdb/consentdb.py
consentdb/models.py
consentdb-0.3.1.dist-info/LICENSE
consentdb-0.3.1.dist-info/METADATA
consentdb-0.3.1.dist-info/WHEEL
consentdb-0.3.1.dist-info/top_level.txt
consentdb-0.3.1.dist-info/RECORD
