Metadata-Version: 2.1
Name: consentdb
Version: 0.3.1
Summary: Holds consent information. Does this person give permission for her or his data to be used?
Home-page: https://github.com/sjoerdk/consentdb
Author: Sjoerd Kerkstra
Author-email: sjoerd.kerkstra@radboudumc.nl
License: MIT license
Keywords: consentdb
Platform: UNKNOWN
Classifier: Development Status :: 2 - Pre-Alpha
Classifier: Intended Audience :: Developers
Classifier: License :: OSI Approved :: MIT License
Classifier: Natural Language :: English
Classifier: Programming Language :: Python :: 3.6
Classifier: Programming Language :: Python :: 3.7
Classifier: Programming Language :: Python :: 3.8
Requires-Python: ~=3.6
Requires-Dist: flask
Requires-Dist: flask-sqlalchemy
Requires-Dist: sqlalchemy
Requires-Dist: mysqlclient
